odoo/addons/l10n_br_contract/README.rst
odoo/addons/l10n_br_contract/__init__.py
odoo/addons/l10n_br_contract/__manifest__.py
odoo/addons/l10n_br_contract/data/company.xml
odoo/addons/l10n_br_contract/demo/company.xml
odoo/addons/l10n_br_contract/demo/contract_demo.xml
odoo/addons/l10n_br_contract/i18n/l10n_br_contract.pot
odoo/addons/l10n_br_contract/i18n/pt_BR.po
odoo/addons/l10n_br_contract/migrations/16.0.5.0.0/pre-migration.py
odoo/addons/l10n_br_contract/models/__init__.py
odoo/addons/l10n_br_contract/models/contract_contract.py
odoo/addons/l10n_br_contract/models/contract_line.py
odoo/addons/l10n_br_contract/models/res_company.py
odoo/addons/l10n_br_contract/readme/CONFIGURE.md
odoo/addons/l10n_br_contract/readme/CONTRIBUTORS.md
odoo/addons/l10n_br_contract/readme/DESCRIPTION.md
odoo/addons/l10n_br_contract/readme/HISTORY.md
odoo/addons/l10n_br_contract/readme/INSTALL.md
odoo/addons/l10n_br_contract/readme/USAGE.md
odoo/addons/l10n_br_contract/static/description/icon.png
odoo/addons/l10n_br_contract/static/description/index.html
odoo/addons/l10n_br_contract/tests/__init__.py
odoo/addons/l10n_br_contract/tests/test_l10n_br_contract.py
odoo/addons/l10n_br_contract/views/contract_line.xml
odoo/addons/l10n_br_contract/views/contract_view.xml
odoo/addons/l10n_br_contract/views/res_company.xml
odoo_addon_l10n_br_contract-16.0.7.0.0.dist-info/METADATA
odoo_addon_l10n_br_contract-16.0.7.0.0.dist-info/WHEEL
odoo_addon_l10n_br_contract-16.0.7.0.0.dist-info/top_level.txt
odoo_addon_l10n_br_contract-16.0.7.0.0.dist-info/RECORD
